{
  "table_id": "table_74",
  "caption": "Table 74. UFQFPN24 - Mechanical data.",
  "pdf_name": "stm32c542cc",
  "family": "C5",
  "page": 104,
  "merged_pages": [
    104
  ],
  "headers": [
    "Symbol",
    "Millimeters / Min",
    "Millimeters / Typ",
    "Millimeters / Max",
    "Inches(1) / Min",
    "Inches(1) / Typ",
    "Inches(1) / Max"
  ],
  "rows": [
    [
      "A",
      "0.45",
      "3Z_UFQFPN24_FP_V1",
      "0.60",
      "0.0177",
      "3Z_UFQFPN24_FP_V1",
      "0.0236"
    ],
    [
      "A1",
      "02.3",
      "3Z_UFQFPN24_FP_V1",
      "0.05",
      "02.3",
      "3Z_UFQFPN24_FP_V1",
      "0.0020"
    ],
    [
      "A3(2)",
      "0.152 REF",
      "0.152 REF",
      "0.152 REF",
      "0.0060 REF",
      "0.0060 REF",
      "0.0060 REF"
    ],
    [
      "L",
      "0.30",
      "0.40",
      "0.50",
      "0.0118",
      "0.0157",
      "0.0197"
    ],
    [
      "b",
      "0.18",
      "0.25",
      "0.30",
      "0.0071",
      "0.0098",
      "0.0118"
    ],
    [
      "D(3)",
      "4.00 BSC",
      "4.00 BSC",
      "4.00 BSC",
      "0.1575 BSC",
      "0.1575 BSC",
      "0.1575 BSC"
    ],
    [
      "E(3)",
      "4.00 BSC",
      "4.00 BSC",
      "4.00 BSC",
      "0.1575 BSC",
      "0.1575 BSC",
      "0.1575 BSC"
    ],
    [
      "e(3)",
      "0.50 BSC",
      "0.50 BSC",
      "0.50 BSC",
      "0.0197 BSC",
      "0.0197 BSC",
      "0.0197 BSC"
    ],
    [
      "D2",
      "2.60",
      "3Z_UFQFPN24_FP_V1",
      "2.85",
      "0.1024",
      "3Z_UFQFPN24_FP_V1",
      "0.1122"
    ],
    [
      "E2",
      "2.60",
      "3Z_UFQFPN24_FP_V1",
      "2.85",
      "0.1024",
      "3Z_UFQFPN24_FP_V1",
      "0.1122"
    ],
    [
      "bbb",
      "3Z_UFQFPN24_FP_V1",
      "0.10",
      "3Z_UFQFPN24_FP_V1",
      "3Z_UFQFPN24_FP_V1",
      "0.0039",
      "3Z_UFQFPN24_FP_V1"
    ],
    [
      "ccc",
      "3Z_UFQFPN24_FP_V1",
      "0.10",
      "3Z_UFQFPN24_FP_V1",
      "3Z_UFQFPN24_FP_V1",
      "0.0039",
      "3Z_UFQFPN24_FP_V1"
    ],
    [
      "eee",
      "3Z_UFQFPN24_FP_V1",
      "0.08",
      "3Z_UFQFPN24_FP_V1",
      "3Z_UFQFPN24_FP_V1",
      "0.0031",
      "3Z_UFQFPN24_FP_V1"
    ],
    [
      "N(4)",
      "24",
      "24",
      "24",
      "24",
      "24",
      "24"
    ]
  ],
  "extraction_method": "pdfplumber",
  "extraction_confidence": "high",
  "empty_cell_ratio": 0.0,
  "col_count": 7,
  "status": null,
  "has_empty_cells": false,
  "heuristics": {
    "cols_extracted": 7
  },
  "structured_json": null,
  "warnings": [
    "dynamic_header_depth:2"
  ],
  "datasheet_metaData": {
    "pdf_name": "stm32c542cc",
    "table_id": "table_74",
    "is_continued": false,
    "pages": [
      104
    ],
    "rows_count": 14,
    "cols_count": 7,
    "confidence": "high",
    "empty_cell_ratio": 0.0
  }
}