{
  "table_id": "table_65",
  "caption": "Table 65. Temperature sensor calibration values.",
  "pdf_name": "stm32f373c8",
  "family": "F3",
  "page": 105,
  "merged_pages": [
    105
  ],
  "headers": [
    "Calibration value name",
    "Description",
    "Memory address"
  ],
  "rows": [
    [
      "TS_CAL1",
      "TS ADC raw data acquired at temperature of 30°C±5°C, V = 3.3V DDA",
      "0x1FFF F7B8 - 0x1FFF F7B9"
    ],
    [
      "TS_CAL2",
      "TS ADC raw data acquired at temperature of 110°C±5°C V = 3.3V DDA",
      "0x1FFF F7C2 - 0x1FFF F7C3"
    ]
  ],
  "extraction_method": "pdfplumber",
  "extraction_confidence": "high",
  "empty_cell_ratio": 0.0,
  "col_count": 3,
  "status": null,
  "has_empty_cells": false,
  "heuristics": {
    "cols_extracted": 3
  },
  "structured_json": null,
  "warnings": [],
  "datasheet_metaData": {
    "pdf_name": "stm32f373c8",
    "table_id": "table_65",
    "is_continued": false,
    "pages": [
      105
    ],
    "rows_count": 2,
    "cols_count": 3,
    "confidence": "high",
    "empty_cell_ratio": 0.0
  }
}