{
  "table_id": "table_9",
  "caption": "Table 9. STM32L151xC and STM32L152xC pin definitions",
  "pdf_name": "stm32l151cc",
  "family": "L1",
  "page": 38,
  "merged_pages": [
    38,
    39,
    40,
    41,
    42,
    43,
    44,
    45
  ],
  "headers": [
    "Pins / UFBGA100",
    "Pins / LQFP100",
    "Pins / LQFP64",
    "Pins / WLCSP63",
    "Pins / LQFP48 or UFQFPN48",
    "Pin name",
    ")1(epyt",
    "I / O Structure",
    "Main",
    "Pin functions / Alternate functions",
    "Pin functions / Additional functions"
  ],
  "rows": [
    [
      "B2",
      "1",
      "-",
      "-",
      "-",
      "PE2",
      "I/O",
      "FT",
      "PE2",
      "TIM3_ETR/LCD_SEG38 /TRACECLK",
      "-"
    ],
    [
      "A1",
      "2",
      "-",
      "-",
      "-",
      "PE3",
      "I/O",
      "FT",
      "PE3",
      "TIM3_CH1/LCD_SEG39 /TRACED0",
      "-"
    ],
    [
      "B1",
      "3",
      "-",
      "-",
      "-",
      "PE4",
      "I/O",
      "FT",
      "PE4",
      "TIM3_CH2/TRACED1",
      "-"
    ],
    [
      "C2",
      "4",
      "-",
      "-",
      "-",
      "PE5",
      "I/O",
      "FT",
      "PE5",
      "TIM9_CH1/TRACED2",
      "-"
    ],
    [
      "D2",
      "5",
      "-",
      "-",
      "-",
      "PE6- WKUP3",
      "I/O",
      "FT",
      "PE6",
      "TIM9_CH2/ TRACED3",
      "WKUP3/ RTC_TAMP3"
    ],
    [
      "E2",
      "6",
      "1",
      "C7",
      "1",
      "V (3) LCD",
      "S",
      "-",
      "V LCD",
      "-",
      "-"
    ],
    [
      "001AGBFU",
      "001PFQL",
      "46PFQL",
      "36PSCLW",
      "84NPFQFU ro 84PFQL",
      "V (3) LCD",
      "S",
      "-",
      "V LCD",
      "Alternate functions",
      "Additional functions"
    ],
    [
      "C1",
      "7",
      "2",
      "D5",
      "2",
      "PC13- WKUP2",
      "I/O",
      "FT",
      "PC13",
      "-",
      "WKUP2/ RTC_TAMP1/ RTC_TS/RTC_OUT"
    ],
    [
      "D1",
      "8",
      "3",
      "D7",
      "3",
      "PC14- OSC32_IN(4)",
      "I/O",
      "TC",
      "PC14",
      "-",
      "OSC32_IN"
    ],
    [
      "E1",
      "9",
      "4",
      "D6",
      "4",
      "PC15- OSC32_OUT",
      "I/O",
      "TC",
      "PC15",
      "-",
      "OSC32_OUT"
    ],
    [
      "F2",
      "10",
      "-",
      "-",
      "-",
      "V SS_5",
      "S",
      "-",
      "V SS_5",
      "-",
      "-"
    ],
    [
      "G2",
      "11",
      "-",
      "-",
      "-",
      "V DD_5",
      "S",
      "-",
      "V DD_5",
      "-",
      "-"
    ],
    [
      "F1",
      "12",
      "5",
      "F6",
      "5",
      "PH0- OSC_IN(5)",
      "I/O",
      "TC",
      "PH0",
      "-",
      "OSC_IN"
    ],
    [
      "G1",
      "13",
      "6",
      "F7",
      "6",
      "PH1- OSC_OUT(5)",
      "I/O",
      "TC",
      "PH1",
      "-",
      "OSC_OUT"
    ],
    [
      "H2",
      "14",
      "7",
      "E7",
      "7",
      "NRST",
      "I/O",
      "RST",
      "NRST",
      "-",
      "-"
    ],
    [
      "H1",
      "15",
      "8",
      "E6",
      "-",
      "PC0",
      "I/O",
      "FT",
      "PC0",
      "LCD_SEG18",
      "ADC_IN10/ COMP1_INP"
    ],
    [
      "J2",
      "16",
      "9",
      "E5",
      "-",
      "PC1",
      "I/O",
      "FT",
      "PC1",
      "LCD_SEG19",
      "ADC_IN11/ COMP1_INP"
    ],
    [
      "J3",
      "17",
      "10",
      "G7",
      "-",
      "PC2",
      "I/O",
      "FT",
      "PC2",
      "LCD_SEG20",
      "ADC_IN12/ COMP1_INP"
    ],
    [
      "K2",
      "18",
      "11",
      "G6",
      "-",
      "PC3",
      "I/O",
      "TC",
      "PC3",
      "LCD_SEG21",
      "ADC_IN13/ COMP1_INP"
    ],
    [
      "J1",
      "19",
      "12",
      "F5",
      "8",
      "V SSA",
      "S",
      "-",
      "V SSA",
      "-",
      "-"
    ],
    [
      "K1",
      "20",
      "-",
      "-",
      "-",
      "V REF-",
      "S",
      "-",
      "V REF-",
      "-",
      "-"
    ],
    [
      "L1",
      "21",
      "-",
      "-",
      "-",
      "V REF+",
      "S",
      "-",
      "V REF+",
      "-",
      "-"
    ],
    [
      "M1",
      "22",
      "13",
      "H7",
      "9",
      "V DDA",
      "S",
      "-",
      "V DDA",
      "-",
      "-"
    ],
    [
      "L2",
      "23",
      "14",
      "E4",
      "10",
      "PA0-WKUP1",
      "I/O",
      "FT",
      "PA0",
      "TIM2_CH1_ETR/ TIM5_CH1/ USART2_CTS",
      "WKUP1/ RTC_TAMP2/ ADC_IN0/ COMP1_INP"
    ],
    [
      "001AGBFU",
      "001PFQL",
      "46PFQL",
      "36PSCLW",
      "84NPFQFU ro 84PFQL",
      "PA0-WKUP1",
      "I/O",
      "FT",
      "PA0",
      "Alternate functions",
      "Additional functions"
    ],
    [
      "M2",
      "24",
      "15",
      "G5",
      "11",
      "PA1",
      "I/O",
      "FT",
      "PA1",
      "TIM2_CH2/TIM5_CH2/ USART2_RTS/ LCD_SEG0",
      "ADC_IN1/ COMP1_INP/ OPAMP1_VINP"
    ],
    [
      "K3",
      "25",
      "16",
      "H6",
      "12",
      "PA2",
      "I/O",
      "FT",
      "PA2",
      "TIM2_CH3/TIM5_CH3/ TIM9_CH1/USART2_TX /LCD_SEG1",
      "ADC_IN2/ COMP1_INP/ OPAMP1_VINM"
    ],
    [
      "L3",
      "26",
      "17",
      "J7",
      "13",
      "PA3",
      "I/O",
      "TC",
      "PA3",
      "TIM2_CH4/TIM5_CH4/ TIM9_CH2/USART2_RX /LCD_SEG2",
      "ADC_IN3/ COMP1_INP/ OPAMP1_VOUT"
    ],
    [
      "E3",
      "27",
      "18",
      "-",
      "-",
      "V SS_4",
      "S",
      "-",
      "V SS_4",
      "-",
      "-"
    ],
    [
      "H3",
      "28",
      "19",
      "-",
      "-",
      "V DD_4",
      "S",
      "-",
      "V DD_4",
      "-",
      "-"
    ],
    [
      "M3",
      "29",
      "20",
      "J6",
      "14",
      "PA4",
      "I/O",
      "TC",
      "PA4",
      "SPI1_NSS/SPI3_NSS/ I2S3_WS/ USART2_CK",
      "ADC_IN4/ DAC_OUT1/ COMP1_INP"
    ],
    [
      "K4",
      "30",
      "21",
      "H4",
      "15",
      "PA5",
      "I/O",
      "TC",
      "PA5",
      "TIM2_CH1_ETR/ SPI1_SCK",
      "ADC_IN5/ DAC_OUT2/ COMP1_INP"
    ],
    [
      "L4",
      "31",
      "22",
      "G4",
      "16",
      "PA6",
      "I/O",
      "FT",
      "PA6",
      "TIM3_CH1/TIM10_CH1/ SPI1_MISO/LCD_SEG3",
      "ADC_IN6/ COMP1_INP/ OPAMP2_VINP"
    ],
    [
      "M4",
      "32",
      "23",
      "J5",
      "17",
      "PA7",
      "I/O",
      "FT",
      "PA7",
      "TIM3_CH2/TIM11_CH1/ SPI1_MOSI/LCD_SEG4",
      "ADC_IN7/ COMP1_INP/ OPAMP2_VINM"
    ],
    [
      "K5",
      "33",
      "24",
      "F4",
      "-",
      "PC4",
      "I/O",
      "FT",
      "PC4",
      "LCD_SEG22",
      "ADC_IN14/ COMP1_INP"
    ],
    [
      "L5",
      "34",
      "25",
      "J4",
      "-",
      "PC5",
      "I/O",
      "FT",
      "PC5",
      "LCD_SEG23",
      "ADC_IN15/ COMP1_INP"
    ],
    [
      "M5",
      "35",
      "26",
      "J3",
      "18",
      "PB0",
      "I/O",
      "TC",
      "PB0",
      "TIM3_CH3/LCD_SEG5",
      "ADC_IN8/ COMP1_INP/ OPAMP2_VOUT/ VLCDRAIL3/ VREF_OUT"
    ],
    [
      "001AGBFU",
      "001PFQL",
      "46PFQL",
      "36PSCLW",
      "84NPFQFU ro 84PFQL",
      "PB0",
      "I/O",
      "TC",
      "PB0",
      "Alternate functions",
      "Additional functions"
    ],
    [
      "M6",
      "36",
      "27",
      "H3",
      "19",
      "PB1",
      "I/O",
      "FT",
      "PB1",
      "TIM3_CH4/LCD_SEG6",
      "ADC_IN9/ COMP1_INP/ VREF_OUT"
    ],
    [
      "L6",
      "37",
      "28",
      "G3",
      "20",
      "PB2",
      "I/O",
      "FT",
      "PB2 /BOOT1",
      "BOOT1",
      "VLCDRAIL1/ ADCIN0b"
    ],
    [
      "M7",
      "38",
      "-",
      "-",
      "-",
      "PE7",
      "I/O",
      "TC",
      "PE7",
      "-",
      "ADC_IN22/ COMP1_INP"
    ],
    [
      "L7",
      "39",
      "-",
      "-",
      "-",
      "PE8",
      "I/O",
      "TC",
      "PE8",
      "-",
      "ADC_IN23/ COMP1_INP"
    ],
    [
      "M8",
      "40",
      "-",
      "-",
      "-",
      "PE9",
      "-",
      "TC",
      "PE9",
      "TIM2_CH1_ETR/ TIM5_ETR",
      "ADC_IN24/ COMP1_INP"
    ],
    [
      "L8",
      "41",
      "-",
      "-",
      "-",
      "PE10",
      "I/O",
      "TC",
      "PE10",
      "TIM2_CH2",
      "ADC_IN25/ COMP1_INP"
    ],
    [
      "M9",
      "42",
      "-",
      "-",
      "-",
      "PE11",
      "I/O",
      "FT",
      "PE11",
      "TIM2_CH3",
      "VLCDRAIL2"
    ],
    [
      "L9",
      "43",
      "-",
      "-",
      "-",
      "PE12",
      "I/O",
      "FT",
      "PE12",
      "TIM2_CH4/SPI1_NSS",
      "VLCDRAIL3"
    ],
    [
      "M10",
      "44",
      "-",
      "-",
      "-",
      "PE13",
      "I/O",
      "FT",
      "PE13",
      "SPI1_SCK",
      "-"
    ],
    [
      "M11",
      "45",
      "-",
      "-",
      "-",
      "PE14",
      "I/O",
      "FT",
      "PE14",
      "SPI1_MISO",
      "-"
    ],
    [
      "M12",
      "46",
      "-",
      "-",
      "-",
      "PE15",
      "I/O",
      "FT",
      "PE15",
      "SPI1_MOSI",
      "-"
    ],
    [
      "L10",
      "47",
      "29",
      "J2",
      "21",
      "PB10",
      "I/O",
      "FT",
      "PB10",
      "TIM2_CH3/I2C2_SCL/ USART3_TX/ LCD_SEG10",
      "-"
    ],
    [
      "L11",
      "48",
      "30",
      "H2",
      "22",
      "PB11",
      "I/O",
      "FT",
      "PB11",
      "TIM2_CH4/I2C2_SDA/ USART3_RX/ LCD_SEG11",
      "-"
    ],
    [
      "-",
      "-",
      "-",
      "H5",
      "-",
      "V SS",
      "S",
      "-",
      "V SS",
      "-",
      "-"
    ],
    [
      "F12",
      "49",
      "31",
      "J1",
      "23",
      "V SS_1",
      "S",
      "-",
      "V SS_1",
      "-",
      "-"
    ],
    [
      "G12",
      "50",
      "32",
      "H1",
      "24",
      "V DD_1",
      "S",
      "-",
      "V DD_1",
      "-",
      "-"
    ],
    [
      "001AGBFU",
      "001PFQL",
      "46PFQL",
      "36PSCLW",
      "84NPFQFU ro 84PFQL",
      "V DD_1",
      "S",
      "-",
      "V DD_1",
      "Alternate functions",
      "Additional functions"
    ],
    [
      "L12",
      "51",
      "33",
      "G2",
      "25",
      "PB12",
      "I/O",
      "FT",
      "PB12",
      "TIM10_CH1 /I2C2_SMBA/ SPI2_NSS/I2S2_WS/ USART3_CK/ LCD_SEG12",
      "ADC_IN18/ COMP1_INP/ VLCDRAIL2"
    ],
    [
      "K12",
      "52",
      "34",
      "G1",
      "26",
      "PB13",
      "I/O",
      "FT",
      "PB13",
      "TIM9_CH1/SPI2_SCK/ I2S2_CK/ USART3_CTS/ LCD_SEG13",
      "ADC_IN19/ COMP1_INP"
    ],
    [
      "K11",
      "53",
      "35",
      "F3",
      "27",
      "PB14",
      "I/O",
      "FT",
      "PB14",
      "TIM9_CH2/SPI2_MISO/ USART3_RTS/ LCD_SEG14",
      "ADC_IN20/ COMP1_INP"
    ],
    [
      "K10",
      "54",
      "36",
      "F2",
      "28",
      "PB15",
      "I/O",
      "FT",
      "PB15",
      "TIM11_CH1/SPI2_MOSI /I2S2_SD/LCD_SEG15",
      "ADC_IN21/ COMP1_INP/ RTC_REFIN"
    ],
    [
      "K9",
      "55",
      "-",
      "-",
      "-",
      "PD8",
      "I/O",
      "FT",
      "PD8",
      "USART3_TX/ LCD_SEG28",
      "-"
    ],
    [
      "K8",
      "56",
      "-",
      "-",
      "-",
      "PD9",
      "I/O",
      "FT",
      "PD9",
      "USART3_RX/ LCD_SEG29",
      "-"
    ],
    [
      "J12",
      "57",
      "-",
      "-",
      "-",
      "PD10",
      "I/O",
      "FT",
      "PD10",
      "USART3_CK/ LCD_SEG30",
      "-"
    ],
    [
      "J11",
      "58",
      "-",
      "-",
      "-",
      "PD11",
      "I/O",
      "FT",
      "PD11",
      "USART3_CTS/ LCD_SEG31",
      "-"
    ],
    [
      "J10",
      "59",
      "-",
      "-",
      "-",
      "PD12",
      "I/O",
      "FT",
      "PD12",
      "TIM4_CH1/ USART3_RTS/ LCD_SEG32",
      "-"
    ],
    [
      "H12",
      "60",
      "-",
      "-",
      "-",
      "PD13",
      "I/O",
      "FT",
      "PD13",
      "TIM4_CH2/LCD_SEG33",
      "-"
    ],
    [
      "H11",
      "61",
      "-",
      "-",
      "-",
      "PD14",
      "I/O",
      "FT",
      "PD14",
      "TIM4_CH3/LCD_SEG34",
      "-"
    ],
    [
      "H10",
      "62",
      "-",
      "-",
      "-",
      "PD15",
      "I/O",
      "FT",
      "PD15",
      "TIM4_CH4/LCD_SEG35",
      "-"
    ],
    [
      "E12",
      "63",
      "37",
      "F1",
      "-",
      "PC6",
      "I/O",
      "FT",
      "PC6",
      "TIM3_CH1/I2S2_MCK/ LCD_SEG24",
      "-"
    ],
    [
      "001AGBFU",
      "001PFQL",
      "46PFQL",
      "36PSCLW",
      "84NPFQFU ro 84PFQL",
      "PC6",
      "I/O",
      "FT",
      "PC6",
      "Alternate functions",
      "Additional functions"
    ],
    [
      "E11",
      "64",
      "38",
      "E1",
      "-",
      "PC7",
      "I/O",
      "FT",
      "PC7",
      "TIM3_CH2/I2S3_MCK/ LCD_SEG25",
      "-"
    ],
    [
      "E10",
      "65",
      "39",
      "D1",
      "-",
      "PC8",
      "I/O",
      "FT",
      "PC8",
      "TIM3_CH3/LCD_SEG26",
      "-"
    ],
    [
      "D12",
      "66",
      "40",
      "E2",
      "-",
      "PC9",
      "I/O",
      "FT",
      "PC9",
      "TIM3_CH4/LCD_SEG27",
      "-"
    ],
    [
      "D11",
      "67",
      "41",
      "E3",
      "29",
      "PA8",
      "I/O",
      "FT",
      "PA8",
      "USART1_CK/MCO/ LCD_COM0",
      "-"
    ],
    [
      "D10",
      "68",
      "42",
      "C1",
      "30",
      "PA9",
      "I/O",
      "FT",
      "PA9",
      "USART1_TX/ LCD_COM1",
      "-"
    ],
    [
      "C12",
      "69",
      "43",
      "D2",
      "31",
      "PA10",
      "I/O",
      "FT",
      "PA10",
      "USART1_RX/ LCD_COM2",
      "-"
    ],
    [
      "B12",
      "70",
      "44",
      "B1",
      "32",
      "PA11",
      "I/O",
      "FT",
      "PA11",
      "USART1_CTS/ SPI1_MISO",
      "USB_DM"
    ],
    [
      "A12",
      "71",
      "45",
      "D3",
      "33",
      "PA12",
      "I/O",
      "FT",
      "PA12",
      "USART1_RTS/ SPI1_MOSI",
      "USB_DP"
    ],
    [
      "A11",
      "72",
      "46",
      "C2",
      "34",
      "PA13",
      "I/O",
      "FT",
      "JTMS- SWDIO",
      "JTMS-SWDIO",
      "-"
    ],
    [
      "C11",
      "73",
      "-",
      "-",
      "-",
      "PH2",
      "I/O",
      "FT",
      "PH2",
      "-",
      "-"
    ],
    [
      "F11",
      "74",
      "47",
      "A1",
      "35",
      "V SS_2",
      "S",
      "-",
      "V SS_2",
      "-",
      "-"
    ],
    [
      "G11",
      "75",
      "48",
      "B2",
      "36",
      "V DD_2",
      "S",
      "-",
      "V DD_2",
      "-",
      "-"
    ],
    [
      "A10",
      "76",
      "49",
      "C3",
      "37",
      "PA14",
      "I/O",
      "FT",
      "JTCK- SWCLK",
      "JTCK-SWCLK",
      "-"
    ],
    [
      "A9",
      "77",
      "50",
      "A2",
      "38",
      "PA15",
      "I/O",
      "FT",
      "JTDI",
      "TIM2_CH1_ETR/ SPI1_NSS/ SPI3_NSS/I2S3_WS/ LCD_SEG17/JTDI",
      "-"
    ],
    [
      "B11",
      "78",
      "51",
      "B3",
      "-",
      "PC10",
      "I/O",
      "FT",
      "PC10",
      "SPI3_SCK/I2S3_CK/ USART3_TX/ LCD_SEG28/ LCD_SEG40/ LCD_COM4",
      "-"
    ],
    [
      "001AGBFU",
      "001PFQL",
      "46PFQL",
      "36PSCLW",
      "84NPFQFU ro 84PFQL",
      "PC10",
      "I/O",
      "FT",
      "PC10",
      "Alternate functions",
      "Additional functions"
    ],
    [
      "C10",
      "79",
      "52",
      "A3",
      "-",
      "PC11",
      "I/O",
      "FT",
      "PC11",
      "SPI3_MISO/ USART3_RX/ LCD_SEG29/ LCD_SEG41/ LCD_COM5",
      "-"
    ],
    [
      "B10",
      "80",
      "53",
      "B4",
      "-",
      "PC12",
      "I/O",
      "FT",
      "PC12",
      "SPI3_MOSI/I2S3_SD/ USART3_CK/ LCD_SEG30/ LCD_SEG42/ LCD_COM6",
      "-"
    ],
    [
      "C9",
      "81",
      "-",
      "-",
      "-",
      "PD0",
      "I/O",
      "FT",
      "PD0",
      "TIM9_CH1/SPI2_NSS/ I2S2_WS",
      "-"
    ],
    [
      "B9",
      "82",
      "-",
      "-",
      "-",
      "PD1",
      "I/O",
      "FT",
      "PD1",
      "SPI2_SCK/I2S2_CK",
      "-"
    ],
    [
      "C8",
      "83",
      "54",
      "A4",
      "-",
      "PD2",
      "I/O",
      "FT",
      "PD2",
      "TIM3_ETR/LCD_SEG31 /LCD_SEG43/ LCD_COM7",
      "-"
    ],
    [
      "B8",
      "84",
      "-",
      "-",
      "-",
      "PD3",
      "I/O",
      "FT",
      "PD3",
      "SPI2_MISO/ USART2_CTS",
      "-"
    ],
    [
      "B7",
      "85",
      "-",
      "-",
      "-",
      "PD4",
      "I/O",
      "FT",
      "PD4",
      "SPI2_MOSI/I2S2_SD/ USART2_RTS",
      "-"
    ],
    [
      "A6",
      "86",
      "-",
      "-",
      "-",
      "PD5",
      "I/O",
      "FT",
      "PD5",
      "USART2_TX",
      "-"
    ],
    [
      "B6",
      "87",
      "-",
      "-",
      "-",
      "PD6",
      "I/O",
      "FT",
      "PD6",
      "USART2_RX",
      "-"
    ],
    [
      "A5",
      "88",
      "-",
      "-",
      "-",
      "PD7",
      "I/O",
      "FT",
      "PD7",
      "TIM9_CH2/USART2_CK",
      "-"
    ],
    [
      "A8",
      "89",
      "55",
      "C4",
      "39",
      "PB3",
      "I/O",
      "FT",
      "JTDO",
      "TIM2_CH2/SPI1_SCK/ SPI3_SCK/I2S3_CK/ LCD_SEG7/JTDO",
      "COMP2_INM"
    ],
    [
      "A7",
      "90",
      "56",
      "D4",
      "40",
      "PB4",
      "I/O",
      "FT",
      "NJTRST",
      "TIM3_CH1/SPI1_MISO/ SPI3_MISO/LCD_SEG8 /NJTRST",
      "COMP2_INP"
    ],
    [
      "C5",
      "91",
      "57",
      "A5",
      "41",
      "PB5",
      "I/O",
      "FT",
      "PB5",
      "TIM3_CH2/I2C1_SMBA/ SPI1_MOSI/SPI3_MOSI /I2S3_SD/LCD_SEG9",
      "COMP2_INP"
    ],
    [
      "001AGBFU",
      "001PFQL",
      "46PFQL",
      "36PSCLW",
      "84NPFQFU ro 84PFQL",
      "PB5",
      "I/O",
      "FT",
      "PB5",
      "Alternate functions",
      "Additional functions"
    ],
    [
      "B5",
      "92",
      "58",
      "B5",
      "42",
      "PB6",
      "I/O",
      "FT",
      "PB6",
      "TIM4_CH1/I2C1_SCL/ USART1_TX",
      "COMP2_INP"
    ],
    [
      "B4",
      "93",
      "59",
      "C5",
      "43",
      "PB7",
      "I/O",
      "FT",
      "PB7",
      "TIM4_CH2/I2C1_SDA/ USART1_RX",
      "COMP2_INP/PVD_IN"
    ],
    [
      "A4",
      "94",
      "60",
      "A6",
      "44",
      "BOOT0",
      "I",
      "B",
      "BOOT0",
      "-",
      "-"
    ],
    [
      "A3",
      "95",
      "61",
      "B6",
      "45",
      "PB8",
      "I/O",
      "FT",
      "PB8",
      "TIM4_CH3/TIM10_CH1/ I2C1_SCL/LCD_SEG16",
      "-"
    ],
    [
      "B3",
      "96",
      "62",
      "C6",
      "46",
      "PB9",
      "I/O",
      "FT",
      "PB9",
      "TIM4_CH4/TIM11_CH1/ I2C1_SDA/LCD_COM3",
      "-"
    ],
    [
      "C3",
      "97",
      "-",
      "-",
      "-",
      "PE0",
      "I/O",
      "FT",
      "PE0",
      "TIM4_ETR/TIM10_CH1/ LCD_SEG36",
      "-"
    ],
    [
      "A2",
      "98",
      "-",
      "-",
      "-",
      "PE1",
      "I/O",
      "FT",
      "PE1",
      "TIM11_CH1/ LCD_SEG37",
      "-"
    ],
    [
      "D3",
      "99",
      "63",
      "A7",
      "47",
      "V SS_3",
      "S",
      "-",
      "V SS_3",
      "-",
      "-"
    ],
    [
      "C4",
      "100",
      "64",
      "B7",
      "48",
      "V DD_3",
      "S",
      "-",
      "V DD_3",
      "-",
      "-"
    ]
  ],
  "extraction_method": "pdfplumber",
  "extraction_confidence": "high",
  "empty_cell_ratio": 0.0,
  "col_count": 11,
  "status": null,
  "has_empty_cells": false,
  "heuristics": {
    "cols_extracted": 11
  },
  "structured_json": null,
  "warnings": [
    "dynamic_header_depth:2",
    "multi_page_merged:8",
    "vertical_merge_suspected"
  ],
  "datasheet_metaData": {
    "pdf_name": "stm32l151cc",
    "table_id": "table_9",
    "is_continued": true,
    "pages": [
      38,
      39,
      40,
      41,
      42,
      43,
      44,
      45
    ],
    "rows_count": 108,
    "cols_count": 11,
    "confidence": "high",
    "empty_cell_ratio": 0.0
  }
}