{
  "table_id": "table_53",
  "caption": "Table 53. I/O static characteristics",
  "pdf_name": "stm32f411cc",
  "family": "F4",
  "page": 98,
  "merged_pages": [
    98
  ],
  "headers": [
    "Symbol",
    "Parameter",
    "Conditions",
    "Min",
    "Typ",
    "Max",
    "Unit"
  ],
  "rows": [
    [
      "V IL",
      "FT, TC and NRST I/O input low level voltage",
      "1.7 V‚Č§ V ‚Č§ 3.6 V DD",
      "-",
      "-",
      "0.3V (1) DD",
      "V"
    ],
    [
      "V IL",
      "BOOT0 I/O input low level voltage",
      "1.75 V‚Č§ V ‚Č§ 3.6 V, DD -40 ¬įC‚Č§ T ‚Č§ 125 ¬įC A",
      "-",
      "-",
      "0.1V +0.1 DD (2)",
      "V"
    ],
    [
      "V IL",
      "BOOT0 I/O input low level voltage",
      "1.7 V‚Č§ V ‚Č§ 3.6 V, DD 0 ¬įC‚Č§ T ‚Č§ 125 ¬įC A",
      "-",
      "-",
      "0.1V +0.1 DD (2)",
      "V"
    ],
    [
      "V IH",
      "FT, TC and NRST I/O input high level voltage(5)",
      "1.7 V‚Č§ V ‚Č§ 3.6 V DD",
      "0.7V (1 DD )",
      "-",
      "-",
      "V"
    ],
    [
      "V IH",
      "BOOT0 I/O input high level voltage",
      "1.75 V‚Č§ V ‚Č§ 3.6 V, DD -40 ¬įC‚Č§ T ‚Č§ 125 ¬įC A",
      "0.17V DD +0.7(2)",
      "-",
      "-",
      "V"
    ],
    [
      "V IH",
      "BOOT0 I/O input high level voltage",
      "1.7 V‚Č§ V ‚Č§ 3.6 V, DD 0 ¬įC‚Č§ T ‚Č§ 125 ¬įC A",
      "0.17V DD +0.7(2)",
      "-",
      "-",
      "V"
    ],
    [
      "V HYS",
      "FT, TC and NRST I/O input hysteresis",
      "1.7 V‚Č§ V ‚Č§ 3.6 V DD",
      "-",
      "10% V (3) DD",
      "-",
      "V"
    ],
    [
      "V HYS",
      "BOOT0 I/O input hysteresis",
      "1.75 V‚Č§ V ‚Č§ 3.6 V, DD -40 ¬įC‚Č§ T ‚Č§ 125 ¬įC A",
      "-",
      "100",
      "-",
      "mV"
    ],
    [
      "V HYS",
      "BOOT0 I/O input hysteresis",
      "1.7 V‚Č§ V ‚Č§ 3.6 V, DD 0 ¬įC‚Č§ T ‚Č§ 125 ¬įC A",
      "-",
      "100",
      "-",
      "mV"
    ],
    [
      "I lkg",
      "I/O input leakage current (4)",
      "V ‚Č§ V ‚Č§ V SS IN DD",
      "-",
      "-",
      "¬Ī1",
      "¬ĶA"
    ],
    [
      "I lkg",
      "I/O FT/TC input leakage current (5)",
      "V = 5 V IN",
      "-",
      "-",
      "3",
      "¬ĶA"
    ]
  ],
  "extraction_method": "pdfplumber",
  "extraction_confidence": "high",
  "empty_cell_ratio": 0.0,
  "col_count": 7,
  "status": null,
  "has_empty_cells": false,
  "heuristics": {
    "cols_extracted": 7
  },
  "structured_json": null,
  "warnings": [],
  "datasheet_metaData": {
    "pdf_name": "stm32f411cc",
    "table_id": "table_53",
    "is_continued": false,
    "pages": [
      98
    ],
    "rows_count": 11,
    "cols_count": 7,
    "confidence": "high",
    "empty_cell_ratio": 0.0
  }
}