{
  "table_id": "table_17",
  "caption": "Table 17. Operating conditions at power-up/power-down.",
  "pdf_name": "stm32c591ce",
  "family": "C5",
  "page": 64,
  "merged_pages": [
    64
  ],
  "headers": [
    "Symbol",
    "Parameter",
    "Min",
    "Max",
    "Unit"
  ],
  "rows": [
    [
      "tVDD",
      "VDD rise‑time rate",
      "0",
      "∞",
      "µs/V"
    ],
    [
      "tVDD",
      "VDD fall‑time rate",
      "0",
      "∞",
      "ms/V"
    ]
  ],
  "extraction_method": "pdfplumber",
  "extraction_confidence": "high",
  "empty_cell_ratio": 0.0,
  "col_count": 5,
  "status": null,
  "has_empty_cells": false,
  "heuristics": {
    "cols_extracted": 5
  },
  "structured_json": null,
  "warnings": [],
  "datasheet_metaData": {
    "pdf_name": "stm32c591ce",
    "table_id": "table_17",
    "is_continued": false,
    "pages": [
      64
    ],
    "rows_count": 2,
    "cols_count": 5,
    "confidence": "high",
    "empty_cell_ratio": 0.0
  }
}