{
  "table_id": "table_43",
  "caption": "Table 43. HSI16 oscillator characteristics",
  "pdf_name": "stm32g483ce",
  "family": "G4",
  "page": 118,
  "merged_pages": [
    118
  ],
  "headers": [
    "Symbol",
    "Parameter",
    "Conditions",
    "Min",
    "Typ",
    "Max",
    "Unit"
  ],
  "rows": [
    [
      "f HSI16",
      "HSI16 Frequency",
      "V =3.0 V, T =30 °C DD A",
      "15.88",
      "-",
      "16.08",
      "MHz"
    ],
    [
      "TRIM",
      "HSI16 user trimming step",
      "Trimming code is not a multiple of 64",
      "0.2",
      "0.3",
      "0.4",
      "%"
    ],
    [
      "TRIM",
      "HSI16 user trimming step",
      "Trimming code is a multiple of 64",
      "-4",
      "-6",
      "-8",
      "%"
    ],
    [
      "DuCy(HSI16)(2)",
      "Duty Cycle",
      "-",
      "45",
      "-",
      "55",
      "%"
    ],
    [
      "∆ (HSI16) Temp",
      "HSI16 oscillator frequency drift over temperature",
      "T = 0 to 85 °C A",
      "-1",
      "-",
      "1",
      "%"
    ],
    [
      "∆ (HSI16) Temp",
      "HSI16 oscillator frequency drift over temperature",
      "T = -40 to 125 °C A",
      "-2",
      "-",
      "1.5",
      "%"
    ],
    [
      "∆ (HSI16) VDD",
      "HSI16 oscillator frequency drift over V DD",
      "V =1.62 V to 3.6 V DD",
      "-0.1",
      "-",
      "0.05",
      "%"
    ],
    [
      "t (HSI16)(2) su",
      "HSI16 oscillator start-up time",
      "-",
      "-",
      "0.8",
      "1.2",
      "μs"
    ],
    [
      "t (HSI16)(2) stab",
      "HSI16 oscillator stabilization time",
      "-",
      "-",
      "3",
      "5",
      "μs"
    ],
    [
      "I (HSI16)(2) DD",
      "HSI16 oscillator power consumption",
      "-",
      "-",
      "155",
      "190",
      "μA"
    ]
  ],
  "extraction_method": "pdfplumber",
  "extraction_confidence": "high",
  "empty_cell_ratio": 0.0,
  "col_count": 7,
  "status": null,
  "has_empty_cells": false,
  "heuristics": {
    "cols_extracted": 7
  },
  "structured_json": null,
  "warnings": [],
  "datasheet_metaData": {
    "pdf_name": "stm32g483ce",
    "table_id": "table_43",
    "is_continued": false,
    "pages": [
      118
    ],
    "rows_count": 10,
    "cols_count": 7,
    "confidence": "high",
    "empty_cell_ratio": 0.0
  }
}