{
  "table_id": "table_30",
  "caption": "Table 30. USB regulator characteristics",
  "pdf_name": "stm32h7b0ab",
  "family": "H7",
  "page": 76,
  "merged_pages": [
    76
  ],
  "headers": [
    "Symbol",
    "Parameter",
    "Conditions",
    "Min",
    "Typ",
    "Max",
    "Unit"
  ],
  "rows": [
    [
      "VDD50USB",
      "Supply voltage",
      "-",
      "4",
      "5",
      "5,5",
      "V"
    ],
    [
      "IDD50USB",
      "Current consumption",
      "-",
      "-",
      "13.5",
      "-",
      "µA"
    ],
    [
      "VREGOUTV33V",
      "Regulated output voltage",
      "-",
      "3",
      "-",
      "3.6",
      "V"
    ],
    [
      "IOUT",
      "Output current load sinked by USB block",
      "-",
      "-",
      "-",
      "20",
      "mA"
    ],
    [
      "TWKUP",
      "Wakeup time",
      "-",
      "-",
      "120",
      "170",
      "µs"
    ]
  ],
  "extraction_method": "pdfplumber",
  "extraction_confidence": "high",
  "empty_cell_ratio": 0.0,
  "col_count": 7,
  "status": null,
  "has_empty_cells": false,
  "heuristics": {
    "cols_extracted": 7
  },
  "structured_json": null,
  "warnings": [
    "vertical_merge_suspected"
  ],
  "datasheet_metaData": {
    "pdf_name": "stm32h7b0ab",
    "table_id": "table_30",
    "is_continued": false,
    "pages": [
      76
    ],
    "rows_count": 5,
    "cols_count": 7,
    "confidence": "high",
    "empty_cell_ratio": 0.0
  }
}