{
  "table_id": "table_7",
  "caption": "Table 7. Securable peripherals by TZSC",
  "pdf_name": "stm32l562ce",
  "family": "L5",
  "page": 30,
  "merged_pages": [
    30,
    31
  ],
  "headers": [
    "Bus",
    "Peripheral"
  ],
  "rows": [
    [
      "AHB3",
      "OCTOSPI1 registers"
    ],
    [
      "AHB3",
      "FMC registers"
    ],
    [
      "AHB 2",
      "SDMMC1"
    ],
    [
      "AHB 2",
      "RNG"
    ],
    [
      "AHB 2",
      "HASH"
    ],
    [
      "AHB 2",
      "AES"
    ],
    [
      "AHB 2",
      "ADC"
    ],
    [
      "AHB1",
      "ICACHE registers"
    ],
    [
      "AHB1",
      "TSC"
    ],
    [
      "AHB1",
      "CRC"
    ],
    [
      "APB2",
      "DFSDM1"
    ],
    [
      "APB2",
      "SAI2"
    ],
    [
      "APB2",
      "SAI1"
    ],
    [
      "APB2",
      "TIM17"
    ],
    [
      "APB2",
      "TIM16"
    ],
    [
      "APB2",
      "TIM15"
    ],
    [
      "APB2",
      "USART1"
    ],
    [
      "APB2",
      "TIM8"
    ],
    [
      "APB2",
      "SPI1"
    ],
    [
      "APB2",
      "TIM1"
    ],
    [
      "APB2",
      "COMP"
    ],
    [
      "APB2",
      "VREFBUF"
    ],
    [
      "APB1",
      "UCPD1"
    ],
    [
      "APB1",
      "USB FS"
    ],
    [
      "APB1",
      "FDCAN1"
    ],
    [
      "APB1",
      "LPTIM3"
    ],
    [
      "APB1",
      "LPTIM2"
    ],
    [
      "APB1",
      "I2C4"
    ],
    [
      "APB1",
      "LPUART1"
    ],
    [
      "APB1",
      "LPTIM1"
    ],
    [
      "APB1",
      "OPAMP"
    ],
    [
      "APB1",
      "DAC1"
    ],
    [
      "APB1",
      "CRS"
    ],
    [
      "APB1",
      "I2C3"
    ],
    [
      "APB1",
      "I2C2"
    ],
    [
      "APB1",
      "I2C1"
    ],
    [
      "APB1",
      "UART5"
    ],
    [
      "APB1",
      "UART4"
    ],
    [
      "APB1",
      "USART3"
    ],
    [
      "APB1",
      "USART2"
    ],
    [
      "APB1",
      "SPI3"
    ],
    [
      "APB1",
      "SPI2"
    ],
    [
      "APB1",
      "IWDG"
    ],
    [
      "APB1",
      "WWDG"
    ],
    [
      "APB1",
      "TIM7"
    ],
    [
      "APB1",
      "TIM6"
    ],
    [
      "APB1",
      "TIM5"
    ],
    [
      "APB1",
      "TIM4"
    ],
    [
      "APB1",
      "TIM3"
    ],
    [
      "APB1",
      "TIM2"
    ]
  ],
  "extraction_method": "pdfplumber",
  "extraction_confidence": "high",
  "empty_cell_ratio": 0.0,
  "col_count": 2,
  "status": null,
  "has_empty_cells": false,
  "heuristics": {
    "cols_extracted": 2
  },
  "structured_json": null,
  "warnings": [
    "multi_page_merged:2",
    "vertical_merge_suspected"
  ],
  "datasheet_metaData": {
    "pdf_name": "stm32l562ce",
    "table_id": "table_7",
    "is_continued": true,
    "pages": [
      30,
      31
    ],
    "rows_count": 50,
    "cols_count": 2,
    "confidence": "high",
    "empty_cell_ratio": 0.0
  }
}