{
  "table_id": "table_106",
  "caption": "Table 106. PSSI transmit characteristics",
  "pdf_name": "stm32n645a0",
  "family": "N6",
  "page": 212,
  "merged_pages": [
    212
  ],
  "headers": [
    "Symbol",
    "Parameter",
    "Conditions",
    "Min",
    "Max",
    "Unit"
  ],
  "rows": [
    [
      "-",
      "Frequency ratio DCMI_PDCK/fHCLK",
      "-",
      "-",
      "0.4",
      "-"
    ],
    [
      "PSSI_PDCK",
      "PSSI clock input",
      "1.65 V ≤ V ≤ 3.6 V DD",
      "-",
      "100(2)",
      "MHz"
    ],
    [
      "D PIXEL",
      "PSSI clock input duty cycle",
      "-",
      "30",
      "70",
      "%"
    ],
    [
      "t SU(DATA)",
      "Data output valid time",
      "1.65 V ≤ V ≤ 3.6 V DD",
      "-",
      "8",
      "ns"
    ],
    [
      "t H(DATA)",
      "Data output hold time",
      "1.65 V ≤ V ≤ 3.6 V DD",
      "5",
      "-",
      "ns"
    ],
    [
      "t SU(DE)",
      "DE output valid time",
      "1.65 V ≤ V ≤ 3.6 V DD",
      "-",
      "8",
      "ns"
    ],
    [
      "t H(DE)",
      "DE output hold time",
      "1.65 V ≤ V ≤ 3.6 V DD",
      "5",
      "-",
      "ns"
    ],
    [
      "t OV(RDY)",
      "RDY input setup time",
      "1.65 V ≤ V ≤ 3.6 V DD",
      "0",
      "-",
      "ns"
    ],
    [
      "t OH(RDY)",
      "RDY input hold time",
      "1.65 V ≤ V ≤ 3.6 V DD",
      "0",
      "-",
      "ns"
    ]
  ],
  "extraction_method": "pdfplumber",
  "extraction_confidence": "high",
  "empty_cell_ratio": 0.0,
  "col_count": 6,
  "status": null,
  "has_empty_cells": false,
  "heuristics": {
    "cols_extracted": 6
  },
  "structured_json": null,
  "warnings": [
    "vertical_merge_suspected"
  ],
  "datasheet_metaData": {
    "pdf_name": "stm32n645a0",
    "table_id": "table_106",
    "is_continued": false,
    "pages": [
      212
    ],
    "rows_count": 9,
    "cols_count": 6,
    "confidence": "high",
    "empty_cell_ratio": 0.0
  }
}