{
  "table_id": "table_2",
  "caption": "Table 2. STM32F437xx and STM32F439xx features and peripheral counts",
  "pdf_name": "stm32f437ai",
  "family": "F4",
  "page": 16,
  "merged_pages": [
    16
  ],
  "headers": [
    "Peripherals",
    "Peripherals",
    "STM32F437",
    "STM32F437 / Vx",
    "STM32F439",
    "STM32F439",
    "STM32F437Zx",
    "STM32F437Zx",
    "STM32F437AI",
    "STM32F439AI",
    "STM32F439Zx",
    "STM32F439Zx",
    "STM32F437Ix",
    "STM32F437Ix",
    "STM32F439Ix",
    "STM32F439Ix",
    "STM32F439Bx",
    "STM32F439Bx",
    "STM32F439Nx",
    "STM32F439Nx"
  ],
  "rows": [
    [
      "Flash memory in Kbytes",
      "Flash memory in Kbytes",
      "1024",
      "2048",
      "1024",
      "2048",
      "1024",
      "2048",
      "2048",
      "2048",
      "1024",
      "2048",
      "1024",
      "2048",
      "1024",
      "2048",
      "1024",
      "2048",
      "1024",
      "2048"
    ],
    [
      "SRAM in Kbytes",
      "System",
      "256(112+16+64+64)",
      "256(112+16+64+64)",
      "256(112+16+64+64)",
      "256(112+16+64+64)",
      "256(112+16+64+64)",
      "256(112+16+64+64)",
      "256(112+16+64+64)",
      "256(112+16+64+64)",
      "256(112+16+64+64)",
      "256(112+16+64+64)",
      "256(112+16+64+64)",
      "256(112+16+64+64)",
      "256(112+16+64+64)",
      "256(112+16+64+64)",
      "256(112+16+64+64)",
      "256(112+16+64+64)",
      "256(112+16+64+64)",
      "256(112+16+64+64)"
    ],
    [
      "SRAM in Kbytes",
      "Backup",
      "4",
      "4",
      "4",
      "4",
      "4",
      "4",
      "4",
      "4",
      "4",
      "4",
      "4",
      "4",
      "4",
      "4",
      "4",
      "4",
      "4",
      "4"
    ],
    [
      "FMC memory controller",
      "FMC memory controller",
      "Yes(1)",
      "Yes(1)",
      "Yes(1)",
      "Yes(1)",
      "Yes(1)",
      "Yes(1)",
      "Yes(1)",
      "Yes(1)",
      "Yes(1)",
      "Yes(1)",
      "Yes(1)",
      "Yes(1)",
      "Yes(1)",
      "Yes(1)",
      "Yes(1)",
      "Yes(1)",
      "Yes(1)",
      "Yes(1)"
    ],
    [
      "Ethernet",
      "Ethernet",
      "Yes",
      "Yes",
      "Yes",
      "Yes",
      "Yes",
      "Yes",
      "Yes",
      "Yes",
      "Yes",
      "Yes",
      "Yes",
      "Yes",
      "Yes",
      "Yes",
      "Yes",
      "Yes",
      "Yes",
      "Yes"
    ],
    [
      "Timers",
      "General- purpose",
      "10",
      "10",
      "10",
      "10",
      "10",
      "10",
      "10",
      "10",
      "10",
      "10",
      "10",
      "10",
      "10",
      "10",
      "10",
      "10",
      "10",
      "10"
    ],
    [
      "Timers",
      "Advance d-control",
      "2",
      "2",
      "2",
      "2",
      "2",
      "2",
      "2",
      "2",
      "2",
      "2",
      "2",
      "2",
      "2",
      "2",
      "2",
      "2",
      "2",
      "2"
    ],
    [
      "Timers",
      "Basic",
      "2",
      "2",
      "2",
      "2",
      "2",
      "2",
      "2",
      "2",
      "2",
      "2",
      "2",
      "2",
      "2",
      "2",
      "2",
      "2",
      "2",
      "2"
    ],
    [
      "Random number generator",
      "Random number generator",
      "Yes",
      "Yes",
      "Yes",
      "Yes",
      "Yes",
      "Yes",
      "Yes",
      "Yes",
      "Yes",
      "Yes",
      "Yes",
      "Yes",
      "Yes",
      "Yes",
      "Yes",
      "Yes",
      "Yes",
      "Yes"
    ],
    [
      "Communication interfaces",
      "SPI / I2S",
      "4/2 (full duplex)(2)",
      "4/2 (full duplex)(2)",
      "4/2 (full duplex)(2)",
      "4/2 (full duplex)(2)",
      "6/2 (full duplex)(2)",
      "6/2 (full duplex)(2)",
      "6/2 (full duplex)(2)",
      "6/2 (full duplex)(2)",
      "6/2 (full duplex)(2)",
      "6/2 (full duplex)(2)",
      "6/2 (full duplex)(2)",
      "6/2 (full duplex)(2)",
      "6/2 (full duplex)(2)",
      "6/2 (full duplex)(2)",
      "6/2 (full duplex)(2)",
      "6/2 (full duplex)(2)",
      "6/2 (full duplex)(2)",
      "6/2 (full duplex)(2)"
    ],
    [
      "Communication interfaces",
      "I2C",
      "3",
      "3",
      "3",
      "3",
      "3",
      "3",
      "3",
      "3",
      "3",
      "3",
      "3",
      "3",
      "3",
      "3",
      "3",
      "3",
      "3",
      "3"
    ],
    [
      "Communication interfaces",
      "USART/ UART",
      "4/4",
      "4/4",
      "4/4",
      "4/4",
      "4/4",
      "4/4",
      "4/4",
      "4/4",
      "4/4",
      "4/4",
      "4/4",
      "4/4",
      "4/4",
      "4/4",
      "4/4",
      "4/4",
      "4/4",
      "4/4"
    ],
    [
      "Communication interfaces",
      "USB OTG FS",
      "Yes",
      "Yes",
      "Yes",
      "Yes",
      "Yes",
      "Yes",
      "Yes",
      "Yes",
      "Yes",
      "Yes",
      "Yes",
      "Yes",
      "Yes",
      "Yes",
      "Yes",
      "Yes",
      "Yes",
      "Yes"
    ],
    [
      "Communication interfaces",
      "USB OTG HS",
      "Yes",
      "Yes",
      "Yes",
      "Yes",
      "Yes",
      "Yes",
      "Yes",
      "Yes",
      "Yes",
      "Yes",
      "Yes",
      "Yes",
      "Yes",
      "Yes",
      "Yes",
      "Yes",
      "Yes",
      "Yes"
    ],
    [
      "Communication interfaces",
      "CAN",
      "2",
      "2",
      "2",
      "2",
      "2",
      "2",
      "2",
      "2",
      "2",
      "2",
      "2",
      "2",
      "2",
      "2",
      "2",
      "2",
      "2",
      "2"
    ],
    [
      "Communication interfaces",
      "SAI",
      "1",
      "1",
      "1",
      "1",
      "1",
      "1",
      "1",
      "1",
      "1",
      "1",
      "1",
      "1",
      "1",
      "1",
      "1",
      "1",
      "1",
      "1"
    ],
    [
      "Communication interfaces",
      "SDIO",
      "Yes",
      "Yes",
      "Yes",
      "Yes",
      "Yes",
      "Yes",
      "Yes",
      "Yes",
      "Yes",
      "Yes",
      "Yes",
      "Yes",
      "Yes",
      "Yes",
      "Yes",
      "Yes",
      "Yes",
      "Yes"
    ],
    [
      "Camera interface",
      "Camera interface",
      "Yes",
      "Yes",
      "Yes",
      "Yes",
      "Yes",
      "Yes",
      "Yes",
      "Yes",
      "Yes",
      "Yes",
      "Yes",
      "Yes",
      "Yes",
      "Yes",
      "Yes",
      "Yes",
      "Yes",
      "Yes"
    ],
    [
      "LCD-TFT",
      "LCD-TFT",
      "No",
      "No",
      "Yes",
      "Yes",
      "No",
      "No",
      "No",
      "Yes",
      "Yes",
      "Yes",
      "No",
      "No",
      "Yes",
      "Yes",
      "Yes",
      "Yes",
      "Yes",
      "Yes"
    ],
    [
      "Chrom-ART Accelerator™ (DMA2D)",
      "Chrom-ART Accelerator™ (DMA2D)",
      "Yes",
      "Yes",
      "Yes",
      "Yes",
      "Yes",
      "Yes",
      "Yes",
      "Yes",
      "Yes",
      "Yes",
      "Yes",
      "Yes",
      "Yes",
      "Yes",
      "Yes",
      "Yes",
      "Yes",
      "Yes"
    ],
    [
      "Cryptography",
      "Cryptography",
      "Yes",
      "Yes",
      "Yes",
      "Yes",
      "Yes",
      "Yes",
      "Yes",
      "Yes",
      "Yes",
      "Yes",
      "Yes",
      "Yes",
      "Yes",
      "Yes",
      "Yes",
      "Yes",
      "Yes",
      "Yes"
    ],
    [
      "GPIOs",
      "GPIOs",
      "82",
      "82",
      "82",
      "82",
      "114",
      "114",
      "114",
      "114",
      "114",
      "114",
      "130",
      "130",
      "130",
      "130",
      "168",
      "168",
      "168",
      "168"
    ]
  ],
  "extraction_method": "pdfplumber",
  "extraction_confidence": "high",
  "empty_cell_ratio": 0.0,
  "col_count": 20,
  "status": null,
  "has_empty_cells": false,
  "heuristics": {
    "cols_extracted": 20
  },
  "structured_json": null,
  "warnings": [
    "dynamic_header_depth:2"
  ],
  "datasheet_metaData": {
    "pdf_name": "stm32f437ai",
    "table_id": "table_2",
    "is_continued": false,
    "pages": [
      16
    ],
    "rows_count": 22,
    "cols_count": 20,
    "confidence": "high",
    "empty_cell_ratio": 0.0
  }
}