{
  "table_id": "table_62",
  "caption": "Table 62. EMI characteristics for fHSE= 8 MHz and fCPU= 200MHz (Setting 2)",
  "pdf_name": "stm32f777bi",
  "family": "F7",
  "page": 154,
  "merged_pages": [
    154
  ],
  "headers": [
    "Symbol",
    "Parameter",
    "Conditions",
    "Monitored",
    "Max vs. / 8/200 MHz",
    "Unit"
  ],
  "rows": [
    [
      "S EMI",
      "Peak (1)",
      "V = 3.6 V, T = 25 °C, TFBGA216 package, DD A conforming to IEC61967-2 ART/L1-cache ON, over-drive ON, all peripheral clocks enabled, clock dithering enabled.",
      "0.1 to 30 MHz",
      "2",
      "dBµV"
    ],
    [
      "S EMI",
      "Peak (1)",
      "V = 3.6 V, T = 25 °C, TFBGA216 package, DD A conforming to IEC61967-2 ART/L1-cache ON, over-drive ON, all peripheral clocks enabled, clock dithering enabled.",
      "30 to 130 MHz",
      "9",
      "dBµV"
    ],
    [
      "S EMI",
      "Peak (1)",
      "V = 3.6 V, T = 25 °C, TFBGA216 package, DD A conforming to IEC61967-2 ART/L1-cache ON, over-drive ON, all peripheral clocks enabled, clock dithering enabled.",
      "130 MHz to 1 GHz",
      "14",
      "dBµV"
    ],
    [
      "S EMI",
      "Peak (1)",
      "V = 3.6 V, T = 25 °C, TFBGA216 package, DD A conforming to IEC61967-2 ART/L1-cache ON, over-drive ON, all peripheral clocks enabled, clock dithering enabled.",
      "1 GHz to 2 GHz",
      "9",
      "dBµV"
    ],
    [
      "S EMI",
      "Level(2)",
      "V = 3.6 V, T = 25 °C, TFBGA216 package, DD A conforming to IEC61967-2 ART/L1-cache ON, over-drive ON, all peripheral clocks enabled, clock dithering enabled.",
      "0.1 to 2 GHz",
      "3",
      "-"
    ]
  ],
  "extraction_method": "pdfplumber",
  "extraction_confidence": "high",
  "empty_cell_ratio": 0.0,
  "col_count": 6,
  "status": null,
  "has_empty_cells": false,
  "heuristics": {
    "cols_extracted": 6
  },
  "structured_json": null,
  "warnings": [
    "dynamic_header_depth:2",
    "vertical_merge_suspected"
  ],
  "datasheet_metaData": {
    "pdf_name": "stm32f777bi",
    "table_id": "table_62",
    "is_continued": false,
    "pages": [
      154
    ],
    "rows_count": 5,
    "cols_count": 6,
    "confidence": "high",
    "empty_cell_ratio": 0.0
  }
}